taxcalc/__init__.py
taxcalc/calcfunctions.py
taxcalc/calculator.py
taxcalc/conftest.py
taxcalc/consumption.json
taxcalc/consumption.py
taxcalc/cps.csv.gz
taxcalc/cps_weights.csv.gz
taxcalc/data.py
taxcalc/decorators.py
taxcalc/growdiff.json
taxcalc/growdiff.py
taxcalc/growfactors.csv
taxcalc/growfactors.py
taxcalc/parameters.py
taxcalc/policy.py
taxcalc/policy_current_law.json
taxcalc/puf_ratios.csv
taxcalc/puf_weights.csv.gz
taxcalc/records.py
taxcalc/records_variables.json
taxcalc/taxcalcio.py
taxcalc/utils.py
taxcalc/utilsprvt.py
taxcalc/assumptions/ASSUMPTIONS.md
taxcalc/assumptions/README.md
taxcalc/assumptions/economic_assumptions_template.json
taxcalc/cli/__init__.py
taxcalc/cli/tc.py
taxcalc/reforms/2017_law.json
taxcalc/reforms/2017_law.out.csv
taxcalc/reforms/ARPA.json
taxcalc/reforms/ARPA.out.csv
taxcalc/reforms/BrownKhanna.json
taxcalc/reforms/BrownKhanna.out.csv
taxcalc/reforms/CARES.json
taxcalc/reforms/CARES.out.csv
taxcalc/reforms/ConsolidatedAppropriationsAct2021.json
taxcalc/reforms/ConsolidatedAppropriationsAct2021.out.csv
taxcalc/reforms/Larson2019.json
taxcalc/reforms/Larson2019.out.csv
taxcalc/reforms/README.md
taxcalc/reforms/REFORMS.md
taxcalc/reforms/Renacci.json
taxcalc/reforms/Renacci.out.csv
taxcalc/reforms/SandersDeFazio.json
taxcalc/reforms/SandersDeFazio.out.csv
taxcalc/reforms/TCJA.json
taxcalc/reforms/TCJA.md
taxcalc/reforms/TCJA.out.csv
taxcalc/reforms/Trump2016.json
taxcalc/reforms/Trump2016.out.csv
taxcalc/reforms/Trump2017.json
taxcalc/reforms/Trump2017.out.csv
taxcalc/reforms/cases.csv
taxcalc/reforms/clp.out.csv
taxcalc/reforms/ext.json
taxcalc/reforms/growfactors_ext.csv
taxcalc/reforms/ptaxes0.json
taxcalc/reforms/ptaxes0.out.csv
taxcalc/reforms/ptaxes1.json
taxcalc/reforms/ptaxes1.out.csv
taxcalc/reforms/ptaxes2.json
taxcalc/reforms/ptaxes2.out.csv
taxcalc/reforms/ptaxes3.json
taxcalc/reforms/ptaxes3.out.csv
taxcalc/reforms/archive/Clinton2016.json
taxcalc/reforms/archive/RyanBrady.json
taxcalc-4.6.1.dist-info/licenses/LICENSE
taxcalc-4.6.1.dist-info/METADATA
taxcalc-4.6.1.dist-info/WHEEL
taxcalc-4.6.1.dist-info/entry_points.txt
taxcalc-4.6.1.dist-info/top_level.txt
taxcalc-4.6.1.dist-info/RECORD
