Metadata-Version: 2.4
Name: taxcalc
Version: 4.6.1
Summary: Tax-Calculator
Home-page: https://github.com/PSLmodels/Tax-Calculator
Download-URL: https://github.com/PSLmodels/Tax-Calculator
License: CC0 1.0 Universal (CC0 1.0) Public Domain Dedication
Classifier: Development Status :: 4 - Beta
Classifier: Intended Audience :: Developers
Classifier: Natural Language :: English
Classifier: License :: CC0 1.0 Universal (CC0 1.0) Public Domain Dedication
Classifier: Operating System :: OS Independent
Classifier: Programming Language :: Python
Classifier: Programming Language :: Python :: 3
Classifier: Programming Language :: Python :: 3.10
Classifier: Programming Language :: Python :: 3.11
Classifier: Programming Language :: Python :: 3.12
Classifier: Topic :: Software Development :: Libraries :: Python Modules
License-File: LICENSE
Requires-Dist: numpy>=1.26
Requires-Dist: pandas>=2.2
Requires-Dist: bokeh>=2.4
Requires-Dist: numba
Requires-Dist: paramtools>=0.19.0
Dynamic: classifier
Dynamic: description
Dynamic: description-content-type
Dynamic: download-url
Dynamic: home-page
Dynamic: license
Dynamic: license-file
Dynamic: requires-dist
Dynamic: summary
